sanitizr/__init__.py
sanitizr/sanitizr/__init__.py
sanitizr/sanitizr/cli/__init__.py
sanitizr/sanitizr/cli/__main__.py
sanitizr/sanitizr/config/__init__.py
sanitizr/sanitizr/config/config.py
sanitizr/sanitizr/core/__init__.py
sanitizr/sanitizr/core/cleaner.py
sanitizr/sanitizr/data/default_params.json
sanitizr-1.0.1.dist-info/licenses/LICENSE
sanitizr-1.0.1.dist-info/METADATA
sanitizr-1.0.1.dist-info/WHEEL
sanitizr-1.0.1.dist-info/entry_points.txt
sanitizr-1.0.1.dist-info/top_level.txt
sanitizr-1.0.1.dist-info/RECORD
