Metadata-Version: 2.4
Name: sanitizr
Version: 1.0.1
Summary: Clean URLs by removing tracking parameters and decoding redirects
Author: Sanitizr Contributors
License: GPL-3.0-or-later
Project-URL: Homepage, https://github.com/Jordonh18/sanitizr
Project-URL: Bug Tracker, https://github.com/Jordonh18/sanitizr/issues
Project-URL: Documentation, https://jordonh18.github.io/sanitizr
Classifier: Development Status :: 5 - Production/Stable
Classifier: Intended Audience :: Developers
Classifier: License :: OSI Approved :: GNU General Public License v3 or later (GPLv3+)
Classifier: Programming Language :: Python :: 3
Classifier: Programming Language :: Python :: 3.8
Classifier: Programming Language :: Python :: 3.9
Classifier: Programming Language :: Python :: 3.10
Classifier: Programming Language :: Python :: 3.11
Classifier: Topic :: Internet :: WWW/HTTP
Classifier: Topic :: Software Development :: Libraries :: Python Modules
Classifier: Topic :: Utilities
Requires-Python: >=3.8
License-File: LICENSE
Provides-Extra: yaml
Requires-Dist: pyyaml>=6.0; extra == "yaml"
Provides-Extra: dev
Requires-Dist: pytest>=7.0; extra == "dev"
Requires-Dist: pytest-cov>=4.0; extra == "dev"
Requires-Dist: black>=23.0; extra == "dev"
Requires-Dist: isort>=5.12; extra == "dev"
Requires-Dist: flake8>=6.0; extra == "dev"
Requires-Dist: mypy>=1.0; extra == "dev"
Requires-Dist: pyyaml>=6.0; extra == "dev"
Provides-Extra: docs
Requires-Dist: mkdocs>=1.4; extra == "docs"
Requires-Dist: mkdocs-material>=9.0; extra == "docs"
Requires-Dist: mkdocstrings>=0.19; extra == "docs"
Requires-Dist: mkdocstrings-python>=0.9; extra == "docs"
Dynamic: license-file
